thread_decorator/__init__.py
thread_decorator/core.py
thread_decorator-0.2.dist-info/LICENSE
thread_decorator-0.2.dist-info/METADATA
thread_decorator-0.2.dist-info/WHEEL
thread_decorator-0.2.dist-info/top_level.txt
thread_decorator-0.2.dist-info/RECORD
